iflow_mcp_viperjuice_code_index_mcp-1.0.0.dist-info/licenses/LICENSE
mcp_server/__init__.py
mcp_server/gateway.py
mcp_server/plugin_base.py
mcp_server/plugin_base_enhanced.py
mcp_server/sync.py
mcp_server/watcher.py
mcp_server/watcher_multi_repo.py
mcp_server/artifacts/commit_artifacts.py
mcp_server/benchmarks/__init__.py
mcp_server/benchmarks/__main__.py
mcp_server/benchmarks/benchmark_runner.py
mcp_server/benchmarks/benchmark_suite.py
mcp_server/benchmarks/mcp_comparison_benchmark.py
mcp_server/benchmarks/quick_comparison.py
mcp_server/benchmarks/run_baseline.py
mcp_server/benchmarks/run_benchmarks.py
mcp_server/cache/__init__.py
mcp_server/cache/backends.py
mcp_server/cache/cache_manager.py
mcp_server/cache/query_cache.py
mcp_server/cli/__init__.py
mcp_server/cli/artifact_commands.py
mcp_server/cli/index_commands.py
mcp_server/cli/index_management.py
mcp_server/cli/repository_commands.py
mcp_server/config/__init__.py
mcp_server/config/environment.py
mcp_server/config/index_paths.py
mcp_server/config/settings.py
mcp_server/config/validation.py
mcp_server/core/__init__.py
mcp_server/core/errors.py
mcp_server/core/ignore_patterns.py
mcp_server/core/logging.py
mcp_server/core/mcp_config_propagator.py
mcp_server/core/path_resolver.py
mcp_server/core/path_utils.py
mcp_server/core/preflight_validator.py
mcp_server/dispatcher/__init__.py
mcp_server/dispatcher/cross_repo_coordinator.py
mcp_server/dispatcher/dispatcher_enhanced.py
mcp_server/dispatcher/plugin_router.py
mcp_server/dispatcher/result_aggregator.py
mcp_server/dispatcher/simple_dispatcher.py
mcp_server/document_processing/__init__.py
mcp_server/document_processing/base_document_plugin.py
mcp_server/document_processing/chunk_optimizer.py
mcp_server/document_processing/contextual_embeddings.py
mcp_server/document_processing/document_interfaces.py
mcp_server/document_processing/metadata_extractor.py
mcp_server/document_processing/semantic_chunker.py
mcp_server/graph/__init__.py
mcp_server/graph/context_selector.py
mcp_server/graph/graph_analyzer.py
mcp_server/graph/interfaces.py
iflow_mcp_viperjuice_code_index_mcp-1.0.0.dist-info/METADATA
iflow_mcp_viperjuice_code_index_mcp-1.0.0.dist-info/WHEEL
iflow_mcp_viperjuice_code_index_mcp-1.0.0.dist-info/entry_points.txt
iflow_mcp_viperjuice_code_index_mcp-1.0.0.dist-info/top_level.txt
iflow_mcp_viperjuice_code_index_mcp-1.0.0.dist-info/RECORD
