Metadata-Version: 2.4
Name: iflow-mcp_viperjuice_code-index-mcp
Version: 1.0.0
Summary: Local-first code indexer for AI assistants via Model Context Protocol (MCP)
Author: Jenner Torrence
License: MIT
Project-URL: Homepage, https://github.com/ViperJuice/Code-Index-MCP
Project-URL: Documentation, https://github.com/ViperJuice/Code-Index-MCP#readme
Project-URL: Repository, https://github.com/ViperJuice/Code-Index-MCP
Project-URL: Issues, https://github.com/ViperJuice/Code-Index-MCP/issues
Keywords: mcp,code-indexer,ai,llm,claude,code-search,tree-sitter
Classifier: Development Status :: 4 - Beta
Classifier: Intended Audience :: Developers
Classifier: License :: OSI Approved :: MIT License
Classifier: Operating System :: OS Independent
Classifier: Programming Language :: Python :: 3
Classifier: Programming Language :: Python :: 3.11
Classifier: Programming Language :: Python :: 3.12
Classifier: Topic :: Software Development :: Libraries :: Python Modules
Classifier: Topic :: Text Processing :: Indexing
Requires-Python: >=3.11
License-File: LICENSE
Requires-Dist: mcp>=1.0.0
Requires-Dist: fastapi>=0.100.0
Requires-Dist: uvicorn>=0.23.0
Requires-Dist: treesitter-chunker>=2.0.0
Requires-Dist: tree-sitter>=0.20.0
Requires-Dist: tree-sitter-languages>=1.7.0
Requires-Dist: jedi>=0.19.0
Requires-Dist: watchdog>=3.0.0
Requires-Dist: click>=8.1.0
Requires-Dist: pydantic>=2.0.0
Requires-Dist: python-dotenv>=1.0.0
Requires-Dist: httpx>=0.24.1
Requires-Dist: pyyaml>=6.0.0
Requires-Dist: voyageai>=0.2.0
Requires-Dist: qdrant-client>=1.7.0
Requires-Dist: numpy>=1.24.0
Requires-Dist: psutil>=5.9.0
Provides-Extra: semantic
Requires-Dist: sentence-transformers>=2.0.0; extra == "semantic"
Requires-Dist: cohere>=4.0.0; extra == "semantic"
Requires-Dist: anthropic>=0.18.0; extra == "semantic"
Provides-Extra: dev
Requires-Dist: pytest>=7.4.0; extra == "dev"
Requires-Dist: pytest-asyncio>=0.21.0; extra == "dev"
Requires-Dist: pytest-cov>=4.1.0; extra == "dev"
Requires-Dist: pytest-timeout>=2.1.0; extra == "dev"
Requires-Dist: pytest-mock>=3.11.1; extra == "dev"
Requires-Dist: pytest-benchmark>=4.0.0; extra == "dev"
Requires-Dist: pytest-xdist>=3.3.1; extra == "dev"
Requires-Dist: black>=23.7.0; extra == "dev"
Requires-Dist: isort>=5.12.0; extra == "dev"
Requires-Dist: mypy>=1.5.1; extra == "dev"
Provides-Extra: all
Requires-Dist: code-index-mcp[dev,semantic]; extra == "all"
Dynamic: license-file
